LICENSE
MANIFEST.in
pypi.rst
setup.cfg
setup.py
supercron/__init__.py
supercron/namespace.py
supercron/repetition_parsing.py
supercron/supercron.py
supercron/trigger.py
supercron/utils.py
supercron.egg-info/PKG-INFO
supercron.egg-info/SOURCES.txt
supercron.egg-info/dependency_links.txt
supercron.egg-info/entry_points.txt
supercron.egg-info/requires.txt
supercron.egg-info/top_level.txt
tests/__init__.py
tests/test_supercron.py