Metadata-Version: 1.1
Name: supercron
Version: 0.3.2
Summary: Intelligent interface to cron in UNIX systems
Home-page: https://linostar.github.io/SuperCron
Author: Anas El Husseini
Author-email: linux.anas@gmail.com
License: BSD
Download-URL: https://github.com/linostar/SuperCron/tarball/0.3.2
Keywords: cron,crontab,scheduling
Platform: UNKNOWN
Classifier: Development Status :: 4 - Beta
Classifier: Environment :: Console
Classifier: Intended Audience :: End Users/Desktop
Classifier: Intended Audience :: System Administrators
Classifier: Topic :: Utilities
Classifier: Topic :: System :: Systems Administration
Classifier: License :: OSI Approved :: BSD License
Classifier: Programming Language :: Python :: 2.7
Classifier: Programming Language :: Python :: 3.3
Classifier: Programming Language :: Python :: 3.4
Classifier: Programming Language :: Python :: 3.5
